hpke/__init__.py
hpke/hpke.py
hpke-0.3.1.dist-info/LICENSE
hpke-0.3.1.dist-info/METADATA
hpke-0.3.1.dist-info/WHEEL
hpke-0.3.1.dist-info/RECORD
