Metadata-Version: 2.1
Name: hpke
Version: 0.3.1
Summary: HPKE implementation
Home-page: https://github.com/ctz/hpke-py
License: Apache-2.0
Author: Joseph Birr-Pixton
Author-email: jpixton@gmail.com
Requires-Python: >=3.8,<4.0
Classifier: License :: OSI Approved :: Apache Software License
Classifier: Programming Language :: Python :: 3
Classifier: Programming Language :: Python :: 3.8
Classifier: Programming Language :: Python :: 3.9
Classifier: Programming Language :: Python :: 3.10
Classifier: Programming Language :: Python :: 3.11
Classifier: Programming Language :: Python :: 3.12
Requires-Dist: cryptography (>=42,<43)
Project-URL: Repository, https://github.com/ctz/hpke-py
